validio_cli/__init__.py
validio_cli/bin/entities/channels.py
validio_cli/bin/entities/code.py
validio_cli/bin/entities/config.py
validio_cli/bin/entities/credentials.py
validio_cli/bin/entities/dbt.py
validio_cli/bin/entities/filters.py
validio_cli/bin/entities/incidents.py
validio_cli/bin/entities/metrics.py
validio_cli/bin/entities/namespaces.py
validio_cli/bin/entities/notification_rules.py
validio_cli/bin/entities/resources.py
validio_cli/bin/entities/segmentations.py
validio_cli/bin/entities/segments.py
validio_cli/bin/entities/sources.py
validio_cli/bin/entities/users.py
validio_cli/bin/entities/validators.py
validio_cli/bin/entities/windows.py
validio_cli/bin/main.py
validio_cli/components.py
validio_cli/metadata.py
validio_cli/namespace.py
validio_cli/schema.py
validio_cli-7.3.1.dist-info/LICENSE
validio_cli-7.3.1.dist-info/METADATA
validio_cli-7.3.1.dist-info/WHEEL
validio_cli-7.3.1.dist-info/entry_points.txt
validio_cli-7.3.1.dist-info/RECORD
