Metadata-Version: 2.1
Name: validio-cli
Version: 7.3.1
Summary: CLI tool to interact with the Validio platform
Home-page: https://validio.io/
License: Apache-2.0
Author: Validio
Author-email: support@validio.io
Requires-Python: >=3.10,<4.0
Classifier: License :: OSI Approved :: Apache Software License
Classifier: Programming Language :: Python :: 3
Classifier: Programming Language :: Python :: 3.10
Classifier: Programming Language :: Python :: 3.11
Requires-Dist: camel-converter (>=3.0.0,<4.0.0)
Requires-Dist: classdiff (>=0.5.0,<0.6.0)
Requires-Dist: prompt-toolkit (>=3.0.38,<4.0.0)
Requires-Dist: tabulate (>=0.9.0,<0.10.0)
Requires-Dist: typer[all] (>=0.8.0,<0.16.0)
Requires-Dist: types-tabulate (>=0.9.0.2,<0.10.0.0)
Requires-Dist: validio-sdk
Project-URL: Documentation, https://docs.validio.io/
